slashlockgui/__init__.py
slashlockgui/gui.py
slashlockgui/patch.py
slashlockgui/kvs/choose_directory_screen.kv
slashlockgui/kvs/drop_screen.kv
slashlockgui/kvs/encrypt_screen.kv
slashlockgui/kvs/file_name_screen.kv
slashlockgui/kvs/gui.kv
slashlockgui/kvs/processing_screen.kv
slashlockgui/kvs/result_screen.kv
slashlockgui/kvs/set_passphrase_screen.kv
slashlockgui/kvs/styles.kv
slashlockgui-0.5.3.dist-info/DESCRIPTION.rst
slashlockgui-0.5.3.dist-info/METADATA
slashlockgui-0.5.3.dist-info/RECORD
slashlockgui-0.5.3.dist-info/WHEEL
slashlockgui-0.5.3.dist-info/entry_points.txt
slashlockgui-0.5.3.dist-info/metadata.json
slashlockgui-0.5.3.dist-info/top_level.txt
