Metadata-Version: 2.0
Name: slashlockgui
Version: 0.5.3
Summary: SlashlockGUI - A simple GUI for Slashlock
Home-page: https://github.com/wookalar/slashlockgui
Author: Aaron Hampton
Author-email: aaron.hampt@gmail.com
License: AGPLv3
Platform: UNKNOWN
Requires-Dist: slashlock (>=0.1.5)
Requires-Dist: Cython (>=0.24.1)
Requires-Dist: Kivy (==1.9.1)
Requires-Dist: Kivy-Garden (>=0.1.4)
